CHANGES.rst
CONTRIBUTORS.rst
DEVELOP.rst
LICENSE.rst
MANIFEST.in
README.rst
setup.cfg
setup.py
docs/HISTORY.txt
docs/INSTALL.txt
docs/LICENSE.GPL
docs/LICENSE.txt
docs/conf.py
docs/index.rst
src/sandia/__init__.py
src/sandia.conferencepolicy.egg-info/PKG-INFO
src/sandia.conferencepolicy.egg-info/SOURCES.txt
src/sandia.conferencepolicy.egg-info/dependency_links.txt
src/sandia.conferencepolicy.egg-info/entry_points.txt
src/sandia.conferencepolicy.egg-info/namespace_packages.txt
src/sandia.conferencepolicy.egg-info/not-zip-safe
src/sandia.conferencepolicy.egg-info/requires.txt
src/sandia.conferencepolicy.egg-info/top_level.txt
src/sandia/conferencepolicy/__init__.py
src/sandia/conferencepolicy/configure.zcml
src/sandia/conferencepolicy/events.zcml
src/sandia/conferencepolicy/interfaces.py
src/sandia/conferencepolicy/patches.py
src/sandia/conferencepolicy/permissions.zcml
src/sandia/conferencepolicy/setuphandlers.py
src/sandia/conferencepolicy/testing.py
src/sandia/conferencepolicy/browser/__init__.py
src/sandia/conferencepolicy/browser/configure.zcml
src/sandia/conferencepolicy/browser/overrides/.gitkeep
src/sandia/conferencepolicy/browser/overrides/plone.app.layout.viewlets.footer.pt
src/sandia/conferencepolicy/browser/overrides/plone.app.layouts.viewlets.colophon.pt
src/sandia/conferencepolicy/browser/static/.gitkeep
src/sandia/conferencepolicy/browser/templates/conference.pt
src/sandia/conferencepolicy/browser/templates/conference_listing.pt
src/sandia/conferencepolicy/browser/templates/person.pt
src/sandia/conferencepolicy/browser/templates/presentation.pt
src/sandia/conferencepolicy/browser/templates/training_class.pt
src/sandia/conferencepolicy/content/__init__.py
src/sandia/conferencepolicy/content/conference.py
src/sandia/conferencepolicy/content/configure.zcml
src/sandia/conferencepolicy/content/keynoter.py
src/sandia/conferencepolicy/content/person.py
src/sandia/conferencepolicy/content/presentation.py
src/sandia/conferencepolicy/content/training_class.py
src/sandia/conferencepolicy/content/vocabularies.py
src/sandia/conferencepolicy/content/models/conference.xml
src/sandia/conferencepolicy/content/models/keynoter.xml
src/sandia/conferencepolicy/content/models/person.xml
src/sandia/conferencepolicy/content/models/presentation.xml
src/sandia/conferencepolicy/content/models/training_class.xml
src/sandia/conferencepolicy/locales/README.rst
