Metadata-Version: 2.1
Name: sandia.conferencepolicy
Version: 1.0a6
Summary: Policy product for Sandia multiconference website
Home-page: https://bitbucket.org/sixfeetup/sandia.conferencepolicy
Author: T. Kim Nguyen
Author-email: kim@sixfeetup.com
License: GPL version 2
Project-URL: PyPI, https://pypi.python.org/pypi/sandia.conferencepolicy
Project-URL: Source, https://bitbucket.org/sixfeetup/sandia.conferencepolicy
Keywords: Python Plone
Platform: UNKNOWN
Classifier: Environment :: Web Environment
Classifier: Framework :: Plone
Classifier: Framework :: Plone :: Addon
Classifier: Framework :: Plone :: 5.2
Classifier: Programming Language :: Python
Classifier: Programming Language :: Python :: 2.7
Classifier: Programming Language :: Python :: 3.6
Classifier: Programming Language :: Python :: 3.7
Classifier: Operating System :: OS Independent
Classifier: License :: OSI Approved :: GNU General Public License v2 (GPLv2)
Requires-Python: ==2.7, >=3.6
Provides-Extra: test
